master/master.srcs/sources_1/new/mast.v
`timescale 1ns / 1ps
//////////////////////////////////////////////////////////////////////////////////
// Company: 
// Engineer: 
// 
// Create Date: 17.09.2019 15:36:52
// Design Name: 
// Module Name: mas_sla
// Project Name: 
// Target Devices: 
// Tool Versions: 
// Description: 
// 
// Dependencies: 
// 
// Revision:
// Revision 0.01 - File Created
// Additional Comments:
// 
//////////////////////////////////////////////////////////////////////////////////


module jmsslaveflipflop(q,qbar,clk,rst,d);
        output reg q;
        output qbar;
        input clk, rst;
        input d;

        assign qbar = ~q;

        always @(posedge clk)
        begin
                if (rst)
                        q <= 0;
                else
                        q <= d;
        end
endmodule

module jmsflipflop(q,qbar,clk,rst,d);
	output q;
	output qbar;
	input clk, rst;
	input d;

	wire iclk, q1, q1bar; // inverted clock and intermediate q output of Master

	assign iclk = ~clk;
	assign qbar = ~q;

	jmsslaveflipflop jmasterff01(q1,q1bar,clk,rst,d);
	jmsslaveflipflop jslaveff02(q,qbar,iclk,rst,q1);

endmodule

master/master.srcs/sim_1/new/mast_tb.v
`timescale 1ns / 1ps
//////////////////////////////////////////////////////////////////////////////////
// Company: 
// Engineer: 
// 
// Create Date: 17.09.2019 15:38:18
// Design Name: 
// Module Name: mas_tb
// Project Name: 
// Target Devices: 
// Tool Versions: 
// Description: 
// 
// Dependencies: 
// 
// Revision:
// Revision 0.01 - File Created
// Additional Comments:
// 
//////////////////////////////////////////////////////////////////////////////////


module jmsflipfloptb;
	wire q, qbar;
	reg clk,rst;
	reg d;

	wire qn_1,qn_1bar; // to monitor current q and previous q values

	jmsflipflop jmsff(q,qbar,clk,rst,d);
//	jdflipflop  jdff(qn_1,qn_1bar,clk,1'b0,q);
  
	always #5 clk = ~clk;
  
  //enabling the wave dump
  initial begin 
    $dumpfile("dump.vcd"); $dumpvars;
  end

	initial
	begin
		d = 0; // JUST keep it initialized
                clk = 1'b0;
		rst = 1; # 20;
		$display("INITIALIZING");
		$display("RSLT\td\tqn_1\tq");
                $display ("PASS\t%d\t%d\t%d",d,qn_1,q);

		rst = 0; # 20;
                $display ("PASS\t%d\t%d\t%d",d,qn_1,q);

		$display("\nTESTING");
		$display("RSLT\td\tqn_1\tq");
                d = 0; # 10; // Another value
                if ( q === 1'b0 ) // Test for inversion
                        $display ("PASS\t%d\t%d\t%d",d,qn_1,q);
                else
                        $display ("FAIL\t%d\t%d\t%d",d,qn_1,q);
		
                d = 1; # 10; // Another value
                if ( q === 1'b0 ) // Test for inversion
                        $display ("PASS\t%d\t%d\t%d",d,qn_1,q);
                else
                        $display ("FAIL\t%d\t%d\t%d",d,qn_1,q);
	
                # 5; // Another value
                if ( q === 1'b1 ) // Test for inversion
                        $display ("PASS\t%d\t%d\t%d",d,qn_1,q);
                else
                        $display ("FAIL\t%d\t%d\t%d",d,qn_1,q);
	
                d = 0; # 5; // Another value
                if ( q === 1'b1 ) // Test for inversion
                        $display ("PASS\t%d\t%d\t%d",d,qn_1,q);
                else
                        $display ("FAIL\t%d\t%d\t%d",d,qn_1,q);
	
                d = 1; # 5; // JUST wait
                if ( q === 1'b0 ) // Test for inversion
                        $display ("PASS\t%d\t%d\t%d",d,qn_1,q);
                else
                        $display ("FAIL\t%d\t%d\t%d",d,qn_1,q);
	
		$finish;	
	end
endmodule

master/master.sim/sim_1/behav/xsim/dump.vcd
$date
   Thu Sep 26 14:31:19 2019
$end
$version
  2019.1
$end
$timescale
  1ps
$end
$scope module jmsflipfloptb $end
$var wire 1 ! q $end
$var wire 1 " qbar $end
$var reg 1 # clk $end
$var reg 1 $ rst $end
$var reg 1 % d $end
$var wire 1 & qn_1 $end
$var wire 1 ' qn_1bar $end
$scope module jmsff $end
$var wire 1 ! q $end
$var wire 1 " qbar $end
$var wire 1 ( clk $end
$var wire 1 ) rst $end
$var wire 1 * d $end
$var wire 1 + iclk $end
$var wire 1 , q1 $end
$var wire 1 - q1bar $end
$scope module jmasterff01 $end
$var reg 1 . q $end
$var wire 1 - qbar $end
$var wire 1 ( clk $end
$var wire 1 ) rst $end
$var wire 1 * d $end
$upscope $end
$scope module jslaveff02 $end
$var reg 1 / q $end
$var wire 1 " qbar $end
$var wire 1 + clk $end
$var wire 1 ) rst $end
$var wire 1 , d $end
$upscope $end
$upscope $end
$upscope $end
$enddefinitions $end
#0
$dumpvars
0!
1"
0#
1$
0%
z&
z'
0(
1)
0*
1+
x,
x-
x.
0/
$end
#5000
1#
1(
0+
0,
1-
0.
#10000
0#
0(
1+
0/
#15000
1#
1(
0+
0.
#20000
0#
0$
0(
0)
1+
0/
#25000
1#
1(
0+
0.
#30000
0#
0(
1+
0/
#35000
1#
1(
0+
0.
#40000
0#
0(
1+
0/
#45000
1#
1(
0+
0.
#50000
0#
1%
0(
1*
1+
0/
#55000
1#
1(
0+
1,
0-
1.
#60000
1!
0"
0#
0(
1+
1/
#65000
1#
0%
1(
0*
0+
0,
1-
0.
#70000
0!
1"
0#
1%
0(
1*
1+
0/
